{
  "meta": {
    "title": "music [MERGED]",
    "bpm": 145
  },
  "offset": 0,
  "scroll": {
    "approach": 1.25
  },
  "notes": [
    {
      "t": 1.407,
      "lane": 1,
      "type": "tap"
    },
    {
      "t": 1.614,
      "lane": 1,
      "type": "tap"
    },
    {
      "t": 1.821,
      "lane": 1,
      "type": "tap"
    },
    {
      "t": 2.028,
      "lane": 1,
      "type": "tap"
    },
    {
      "t": 3.89,
      "lane": 1,
      "type": "tap"
    },
    {
      "t": 4.097,
      "lane": 1,
      "type": "tap"
    },
    {
      "t": 4.303,
      "lane": 1,
      "type": "tap"
    },
    {
      "t": 4.51,
      "lane": 1,
      "type": "tap"
    },
    {
      "t": 4.717,
      "lane": 1,
      "type": "tap"
    },
    {
      "t": 4.924,
      "lane": 1,
      "type": "tap"
    },
    {
      "t": 5.131,
      "lane": 1,
      "type": "tap"
    },
    {
      "t": 5.338,
      "lane": 1,
      "type": "tap"
    },
    {
      "t": 5.545,
      "lane": 1,
      "type": "tap"
    },
    {
      "t": 5.752,
      "lane": 1,
      "type": "tap"
    },
    {
      "t": 5.959,
      "lane": 1,
      "type": "tap"
    },
    {
      "t": 6.372,
      "lane": 1,
      "type": "tap"
    },
    {
      "t": 6.579,
      "lane": 1,
      "type": "tap"
    },
    {
      "t": 6.786,
      "lane": 1,
      "type": "tap"
    },
    {
      "t": 6.993,
      "lane": 1,
      "type": "tap"
    },
    {
      "t": 7.2,
      "lane": 1,
      "type": "tap"
    },
    {
      "t": 7.407,
      "lane": 1,
      "type": "tap"
    },
    {
      "t": 7.614,
      "lane": 1,
      "type": "tap"
    },
    {
      "t": 7.821,
      "lane": 1,
      "type": "tap"
    },
    {
      "t": 8.028,
      "lane": 1,
      "type": "tap"
    },
    {
      "t": 8.234,
      "lane": 1,
      "type": "tap"
    },
    {
      "t": 8.441,
      "lane": 1,
      "type": "tap"
    },
    {
      "t": 8.648,
      "lane": 1,
      "type": "tap"
    },
    {
      "t": 8.855,
      "lane": 1,
      "type": "tap"
    },
    {
      "t": 9.062,
      "lane": 1,
      "type": "tap"
    },
    {
      "t": 9.269,
      "lane": 1,
      "type": "tap"
    },
    {
      "t": 9.476,
      "lane": 1,
      "type": "tap"
    },
    {
      "t": 9.683,
      "lane": 1,
      "type": "tap"
    },
    {
      "t": 10.097,
      "lane": 1,
      "type": "tap"
    },
    {
      "t": 10.51,
      "lane": 1,
      "type": "tap"
    },
    {
      "t": 10.717,
      "lane": 1,
      "type": "tap"
    },
    {
      "t": 10.924,
      "lane": 1,
      "type": "tap"
    },
    {
      "t": 11.338,
      "lane": 1,
      "type": "tap"
    },
    {
      "t": 11.752,
      "lane": 1,
      "type": "tap"
    },
    {
      "t": 12.166,
      "lane": 1,
      "type": "tap"
    },
    {
      "t": 12.372,
      "lane": 1,
      "type": "tap"
    },
    {
      "t": 12.579,
      "lane": 1,
      "type": "tap"
    },
    {
      "t": 12.993,
      "lane": 1,
      "type": "tap"
    },
    {
      "t": 13.407,
      "lane": 1,
      "type": "tap"
    },
    {
      "t": 13.821,
      "lane": 1,
      "type": "tap"
    },
    {
      "t": 14.028,
      "lane": 1,
      "type": "tap"
    },
    {
      "t": 14.234,
      "lane": 1,
      "type": "tap"
    },
    {
      "t": 14.441,
      "lane": 1,
      "type": "tap"
    },
    {
      "t": 14.648,
      "lane": 1,
      "type": "tap"
    },
    {
      "t": 15.062,
      "lane": 1,
      "type": "tap"
    },
    {
      "t": 15.476,
      "lane": 1,
      "type": "tap"
    },
    {
      "t": 15.683,
      "lane": 1,
      "type": "tap"
    },
    {
      "t": 15.89,
      "lane": 1,
      "type": "tap"
    },
    {
      "t": 16.097,
      "lane": 1,
      "type": "tap"
    },
    {
      "t": 16.303,
      "lane": 1,
      "type": "tap"
    },
    {
      "t": 16.51,
      "lane": 1,
      "type": "tap"
    },
    {
      "t": 16.717,
      "lane": 1,
      "type": "tap"
    },
    {
      "t": 16.924,
      "lane": 1,
      "type": "tap"
    },
    {
      "t": 17.131,
      "lane": 1,
      "type": "tap"
    },
    {
      "t": 17.338,
      "lane": 1,
      "type": "tap"
    },
    {
      "t": 17.545,
      "lane": 1,
      "type": "tap"
    },
    {
      "t": 17.752,
      "lane": 1,
      "type": "tap"
    },
    {
      "t": 19.2,
      "lane": 1,
      "type": "tap"
    },
    {
      "t": 19.407,
      "lane": 1,
      "type": "tap"
    },
    {
      "t": 19.614,
      "lane": 1,
      "type": "tap"
    },
    {
      "t": 19.821,
      "lane": 1,
      "type": "tap"
    },
    {
      "t": 20.028,
      "lane": 1,
      "type": "tap"
    },
    {
      "t": 20.234,
      "lane": 1,
      "type": "tap"
    },
    {
      "t": 20.441,
      "lane": 1,
      "type": "tap"
    },
    {
      "t": 20.648,
      "lane": 1,
      "type": "tap"
    },
    {
      "t": 20.855,
      "lane": 1,
      "type": "tap"
    },
    {
      "t": 21.062,
      "lane": 1,
      "type": "tap"
    },
    {
      "t": 21.269,
      "lane": 1,
      "type": "tap"
    },
    {
      "t": 21.476,
      "lane": 1,
      "type": "tap"
    },
    {
      "t": 21.683,
      "lane": 1,
      "type": "tap"
    },
    {
      "t": 21.89,
      "lane": 1,
      "type": "tap"
    },
    {
      "t": 22.097,
      "lane": 1,
      "type": "tap"
    },
    {
      "t": 22.303,
      "lane": 1,
      "type": "tap"
    },
    {
      "t": 22.51,
      "lane": 1,
      "type": "tap"
    },
    {
      "t": 22.717,
      "lane": 1,
      "type": "tap"
    },
    {
      "t": 22.924,
      "lane": 1,
      "type": "tap"
    },
    {
      "t": 23.131,
      "lane": 1,
      "type": "tap"
    },
    {
      "t": 23.338,
      "lane": 1,
      "type": "tap"
    },
    {
      "t": 23.545,
      "lane": 1,
      "type": "tap"
    },
    {
      "t": 23.752,
      "lane": 1,
      "type": "tap"
    },
    {
      "t": 23.959,
      "lane": 1,
      "type": "tap"
    },
    {
      "t": 24.166,
      "lane": 1,
      "type": "tap"
    },
    {
      "t": 24.579,
      "lane": 1,
      "type": "tap"
    },
    {
      "t": 24.786,
      "lane": 1,
      "type": "tap"
    },
    {
      "t": 24.993,
      "lane": 1,
      "type": "tap"
    },
    {
      "t": 25.2,
      "lane": 1,
      "type": "tap"
    },
    {
      "t": 25.407,
      "lane": 1,
      "type": "tap"
    },
    {
      "t": 25.614,
      "lane": 1,
      "type": "tap"
    },
    {
      "t": 25.821,
      "lane": 1,
      "type": "tap"
    },
    {
      "t": 26.028,
      "lane": 1,
      "type": "tap"
    },
    {
      "t": 26.234,
      "lane": 1,
      "type": "tap"
    },
    {
      "t": 26.441,
      "lane": 1,
      "type": "tap"
    },
    {
      "t": 26.648,
      "lane": 1,
      "type": "tap"
    },
    {
      "t": 26.855,
      "lane": 1,
      "type": "tap"
    },
    {
      "t": 27.062,
      "lane": 1,
      "type": "tap"
    },
    {
      "t": 27.269,
      "lane": 1,
      "type": "tap"
    },
    {
      "t": 27.476,
      "lane": 1,
      "type": "tap"
    },
    {
      "t": 27.683,
      "lane": 1,
      "type": "tap"
    },
    {
      "t": 27.89,
      "lane": 1,
      "type": "tap"
    },
    {
      "t": 28.097,
      "lane": 1,
      "type": "tap"
    },
    {
      "t": 28.303,
      "lane": 1,
      "type": "tap"
    },
    {
      "t": 28.51,
      "lane": 1,
      "type": "tap"
    },
    {
      "t": 28.717,
      "lane": 1,
      "type": "tap"
    },
    {
      "t": 28.924,
      "lane": 1,
      "type": "tap"
    },
    {
      "t": 29.131,
      "lane": 1,
      "type": "tap"
    },
    {
      "t": 29.338,
      "lane": 1,
      "type": "tap"
    },
    {
      "t": 29.752,
      "lane": 1,
      "type": "tap"
    },
    {
      "t": 29.959,
      "lane": 1,
      "type": "tap"
    },
    {
      "t": 30.166,
      "lane": 1,
      "type": "tap"
    },
    {
      "t": 30.372,
      "lane": 1,
      "type": "tap"
    },
    {
      "t": 30.579,
      "lane": 1,
      "type": "tap"
    },
    {
      "t": 30.786,
      "lane": 1,
      "type": "tap"
    },
    {
      "t": 30.993,
      "lane": 1,
      "type": "tap"
    },
    {
      "t": 31.2,
      "lane": 1,
      "type": "tap"
    },
    {
      "t": 31.614,
      "lane": 1,
      "type": "tap"
    },
    {
      "t": 31.821,
      "lane": 1,
      "type": "tap"
    },
    {
      "t": 32.028,
      "lane": 1,
      "type": "tap"
    },
    {
      "t": 32.234,
      "lane": 1,
      "type": "tap"
    },
    {
      "t": 32.441,
      "lane": 1,
      "type": "tap"
    },
    {
      "t": 32.648,
      "lane": 1,
      "type": "tap"
    },
    {
      "t": 32.855,
      "lane": 1,
      "type": "tap"
    },
    {
      "t": 33.062,
      "lane": 1,
      "type": "tap"
    },
    {
      "t": 33.269,
      "lane": 1,
      "type": "tap"
    },
    {
      "t": 33.476,
      "lane": 1,
      "type": "tap"
    },
    {
      "t": 33.683,
      "lane": 1,
      "type": "tap"
    },
    {
      "t": 33.89,
      "lane": 1,
      "type": "tap"
    },
    {
      "t": 34.097,
      "lane": 1,
      "type": "tap"
    },
    {
      "t": 34.303,
      "lane": 1,
      "type": "tap"
    },
    {
      "t": 34.51,
      "lane": 1,
      "type": "tap"
    },
    {
      "t": 34.717,
      "lane": 1,
      "type": "tap"
    },
    {
      "t": 34.924,
      "lane": 1,
      "type": "tap"
    },
    {
      "t": 35.338,
      "lane": 1,
      "type": "tap"
    },
    {
      "t": 35.752,
      "lane": 1,
      "type": "tap"
    },
    {
      "t": 35.959,
      "lane": 1,
      "type": "tap"
    },
    {
      "t": 36.166,
      "lane": 1,
      "type": "tap"
    },
    {
      "t": 36.579,
      "lane": 1,
      "type": "tap"
    },
    {
      "t": 36.786,
      "lane": 1,
      "type": "tap"
    },
    {
      "t": 36.993,
      "lane": 1,
      "type": "tap"
    },
    {
      "t": 37.2,
      "lane": 1,
      "type": "tap"
    },
    {
      "t": 37.407,
      "lane": 1,
      "type": "tap"
    },
    {
      "t": 37.614,
      "lane": 1,
      "type": "tap"
    },
    {
      "t": 37.821,
      "lane": 1,
      "type": "tap"
    },
    {
      "t": 38.234,
      "lane": 1,
      "type": "tap"
    },
    {
      "t": 38.648,
      "lane": 1,
      "type": "tap"
    },
    {
      "t": 38.855,
      "lane": 1,
      "type": "tap"
    },
    {
      "t": 39.062,
      "lane": 1,
      "type": "tap"
    },
    {
      "t": 39.476,
      "lane": 1,
      "type": "tap"
    },
    {
      "t": 39.89,
      "lane": 1,
      "type": "tap"
    },
    {
      "t": 40.097,
      "lane": 1,
      "type": "tap"
    },
    {
      "t": 40.303,
      "lane": 1,
      "type": "tap"
    },
    {
      "t": 40.717,
      "lane": 1,
      "type": "tap"
    },
    {
      "t": 40.924,
      "lane": 1,
      "type": "tap"
    },
    {
      "t": 41.131,
      "lane": 1,
      "type": "tap"
    },
    {
      "t": 41.338,
      "lane": 1,
      "type": "tap"
    },
    {
      "t": 41.545,
      "lane": 1,
      "type": "tap"
    },
    {
      "t": 41.959,
      "lane": 1,
      "type": "tap"
    },
    {
      "t": 42.372,
      "lane": 1,
      "type": "tap"
    },
    {
      "t": 42.579,
      "lane": 1,
      "type": "tap"
    },
    {
      "t": 42.786,
      "lane": 1,
      "type": "tap"
    },
    {
      "t": 42.993,
      "lane": 1,
      "type": "tap"
    },
    {
      "t": 43.2,
      "lane": 1,
      "type": "tap"
    },
    {
      "t": 43.407,
      "lane": 1,
      "type": "tap"
    },
    {
      "t": 43.614,
      "lane": 1,
      "type": "tap"
    },
    {
      "t": 43.821,
      "lane": 1,
      "type": "tap"
    },
    {
      "t": 44.028,
      "lane": 1,
      "type": "tap"
    },
    {
      "t": 44.234,
      "lane": 1,
      "type": "tap"
    },
    {
      "t": 44.441,
      "lane": 1,
      "type": "tap"
    },
    {
      "t": 44.648,
      "lane": 1,
      "type": "tap"
    },
    {
      "t": 44.855,
      "lane": 1,
      "type": "tap"
    },
    {
      "t": 45.062,
      "lane": 1,
      "type": "tap"
    },
    {
      "t": 45.269,
      "lane": 1,
      "type": "tap"
    },
    {
      "t": 45.476,
      "lane": 1,
      "type": "tap"
    },
    {
      "t": 45.683,
      "lane": 1,
      "type": "tap"
    },
    {
      "t": 45.89,
      "lane": 1,
      "type": "tap"
    },
    {
      "t": 46.097,
      "lane": 1,
      "type": "tap"
    },
    {
      "t": 46.303,
      "lane": 1,
      "type": "tap"
    },
    {
      "t": 46.51,
      "lane": 1,
      "type": "tap"
    },
    {
      "t": 46.717,
      "lane": 1,
      "type": "tap"
    },
    {
      "t": 47.131,
      "lane": 1,
      "type": "tap"
    },
    {
      "t": 47.338,
      "lane": 1,
      "type": "tap"
    },
    {
      "t": 47.545,
      "lane": 1,
      "type": "tap"
    },
    {
      "t": 47.959,
      "lane": 1,
      "type": "tap"
    },
    {
      "t": 48.372,
      "lane": 1,
      "type": "tap"
    },
    {
      "t": 48.579,
      "lane": 1,
      "type": "tap"
    },
    {
      "t": 48.786,
      "lane": 1,
      "type": "tap"
    },
    {
      "t": 48.993,
      "lane": 1,
      "type": "tap"
    },
    {
      "t": 49.2,
      "lane": 1,
      "type": "tap"
    },
    {
      "t": 49.614,
      "lane": 1,
      "type": "tap"
    },
    {
      "t": 49.821,
      "lane": 1,
      "type": "tap"
    },
    {
      "t": 50.028,
      "lane": 1,
      "type": "tap"
    },
    {
      "t": 50.234,
      "lane": 1,
      "type": "tap"
    },
    {
      "t": 50.441,
      "lane": 1,
      "type": "tap"
    },
    {
      "t": 50.648,
      "lane": 1,
      "type": "tap"
    },
    {
      "t": 50.855,
      "lane": 1,
      "type": "tap"
    },
    {
      "t": 51.062,
      "lane": 1,
      "type": "tap"
    },
    {
      "t": 51.476,
      "lane": 1,
      "type": "tap"
    },
    {
      "t": 51.683,
      "lane": 1,
      "type": "tap"
    },
    {
      "t": 51.89,
      "lane": 1,
      "type": "tap"
    },
    {
      "t": 52.097,
      "lane": 1,
      "type": "tap"
    },
    {
      "t": 52.303,
      "lane": 1,
      "type": "tap"
    },
    {
      "t": 52.51,
      "lane": 1,
      "type": "tap"
    },
    {
      "t": 52.924,
      "lane": 1,
      "type": "tap"
    },
    {
      "t": 53.131,
      "lane": 1,
      "type": "tap"
    },
    {
      "t": 53.338,
      "lane": 1,
      "type": "tap"
    },
    {
      "t": 53.545,
      "lane": 1,
      "type": "tap"
    },
    {
      "t": 53.752,
      "lane": 1,
      "type": "tap"
    },
    {
      "t": 53.959,
      "lane": 1,
      "type": "tap"
    },
    {
      "t": 54.166,
      "lane": 1,
      "type": "tap"
    },
    {
      "t": 54.579,
      "lane": 1,
      "type": "tap"
    },
    {
      "t": 54.993,
      "lane": 1,
      "type": "tap"
    },
    {
      "t": 55.2,
      "lane": 1,
      "type": "tap"
    },
    {
      "t": 55.407,
      "lane": 1,
      "type": "tap"
    },
    {
      "t": 55.614,
      "lane": 1,
      "type": "tap"
    },
    {
      "t": 55.821,
      "lane": 1,
      "type": "tap"
    },
    {
      "t": 56.028,
      "lane": 1,
      "type": "tap"
    },
    {
      "t": 56.234,
      "lane": 1,
      "type": "tap"
    },
    {
      "t": 56.441,
      "lane": 1,
      "type": "tap"
    },
    {
      "t": 56.648,
      "lane": 1,
      "type": "tap"
    },
    {
      "t": 56.855,
      "lane": 1,
      "type": "tap"
    },
    {
      "t": 57.062,
      "lane": 1,
      "type": "tap"
    },
    {
      "t": 57.269,
      "lane": 1,
      "type": "tap"
    },
    {
      "t": 57.476,
      "lane": 1,
      "type": "tap"
    },
    {
      "t": 57.683,
      "lane": 1,
      "type": "tap"
    },
    {
      "t": 57.89,
      "lane": 1,
      "type": "tap"
    },
    {
      "t": 58.097,
      "lane": 1,
      "type": "tap"
    },
    {
      "t": 58.303,
      "lane": 1,
      "type": "tap"
    },
    {
      "t": 58.51,
      "lane": 1,
      "type": "tap"
    },
    {
      "t": 58.717,
      "lane": 1,
      "type": "tap"
    },
    {
      "t": 58.924,
      "lane": 1,
      "type": "tap"
    },
    {
      "t": 59.131,
      "lane": 1,
      "type": "tap"
    },
    {
      "t": 59.338,
      "lane": 1,
      "type": "tap"
    },
    {
      "t": 59.545,
      "lane": 1,
      "type": "tap"
    },
    {
      "t": 59.752,
      "lane": 1,
      "type": "tap"
    },
    {
      "t": 59.959,
      "lane": 1,
      "type": "tap"
    },
    {
      "t": 60.166,
      "lane": 1,
      "type": "tap"
    },
    {
      "t": 60.372,
      "lane": 1,
      "type": "tap"
    },
    {
      "t": 60.579,
      "lane": 1,
      "type": "tap"
    },
    {
      "t": 60.786,
      "lane": 1,
      "type": "tap"
    },
    {
      "t": 60.993,
      "lane": 1,
      "type": "tap"
    },
    {
      "t": 61.2,
      "lane": 1,
      "type": "tap"
    },
    {
      "t": 61.407,
      "lane": 1,
      "type": "tap"
    },
    {
      "t": 61.614,
      "lane": 1,
      "type": "tap"
    },
    {
      "t": 61.821,
      "lane": 1,
      "type": "tap"
    },
    {
      "t": 62.028,
      "lane": 1,
      "type": "tap"
    },
    {
      "t": 62.234,
      "lane": 1,
      "type": "tap"
    },
    {
      "t": 62.441,
      "lane": 1,
      "type": "tap"
    },
    {
      "t": 62.648,
      "lane": 1,
      "type": "tap"
    },
    {
      "t": 62.855,
      "lane": 1,
      "type": "tap"
    },
    {
      "t": 63.062,
      "lane": 1,
      "type": "tap"
    },
    {
      "t": 63.269,
      "lane": 1,
      "type": "tap"
    },
    {
      "t": 63.476,
      "lane": 1,
      "type": "tap"
    },
    {
      "t": 63.683,
      "lane": 1,
      "type": "tap"
    },
    {
      "t": 63.89,
      "lane": 1,
      "type": "tap"
    },
    {
      "t": 64.097,
      "lane": 1,
      "type": "tap"
    },
    {
      "t": 64.303,
      "lane": 1,
      "type": "tap"
    },
    {
      "t": 64.717,
      "lane": 1,
      "type": "tap"
    },
    {
      "t": 64.924,
      "lane": 1,
      "type": "tap"
    },
    {
      "t": 65.131,
      "lane": 1,
      "type": "tap"
    },
    {
      "t": 65.338,
      "lane": 1,
      "type": "tap"
    },
    {
      "t": 65.545,
      "lane": 1,
      "type": "tap"
    },
    {
      "t": 65.752,
      "lane": 1,
      "type": "tap"
    },
    {
      "t": 65.959,
      "lane": 1,
      "type": "tap"
    },
    {
      "t": 66.166,
      "lane": 1,
      "type": "tap"
    },
    {
      "t": 66.372,
      "lane": 1,
      "type": "tap"
    },
    {
      "t": 66.579,
      "lane": 1,
      "type": "tap"
    },
    {
      "t": 66.786,
      "lane": 1,
      "type": "tap"
    },
    {
      "t": 66.993,
      "lane": 1,
      "type": "tap"
    },
    {
      "t": 67.2,
      "lane": 1,
      "type": "tap"
    },
    {
      "t": 67.614,
      "lane": 1,
      "type": "tap"
    },
    {
      "t": 68.028,
      "lane": 1,
      "type": "tap"
    },
    {
      "t": 68.234,
      "lane": 1,
      "type": "tap"
    },
    {
      "t": 68.441,
      "lane": 1,
      "type": "tap"
    },
    {
      "t": 68.648,
      "lane": 1,
      "type": "tap"
    },
    {
      "t": 68.855,
      "lane": 1,
      "type": "tap"
    },
    {
      "t": 69.062,
      "lane": 1,
      "type": "tap"
    },
    {
      "t": 69.269,
      "lane": 1,
      "type": "tap"
    },
    {
      "t": 69.683,
      "lane": 1,
      "type": "tap"
    },
    {
      "t": 70.097,
      "lane": 1,
      "type": "tap"
    },
    {
      "t": 70.303,
      "lane": 1,
      "type": "tap"
    },
    {
      "t": 70.51,
      "lane": 1,
      "type": "tap"
    },
    {
      "t": 70.717,
      "lane": 1,
      "type": "tap"
    },
    {
      "t": 70.924,
      "lane": 1,
      "type": "tap"
    },
    {
      "t": 71.131,
      "lane": 1,
      "type": "tap"
    },
    {
      "t": 71.338,
      "lane": 1,
      "type": "tap"
    },
    {
      "t": 71.752,
      "lane": 1,
      "type": "tap"
    },
    {
      "t": 72.166,
      "lane": 1,
      "type": "tap"
    },
    {
      "t": 72.372,
      "lane": 1,
      "type": "tap"
    },
    {
      "t": 72.579,
      "lane": 1,
      "type": "tap"
    },
    {
      "t": 72.786,
      "lane": 1,
      "type": "tap"
    },
    {
      "t": 73.407,
      "lane": 1,
      "type": "tap"
    },
    {
      "t": 73.614,
      "lane": 1,
      "type": "tap"
    },
    {
      "t": 73.821,
      "lane": 1,
      "type": "tap"
    },
    {
      "t": 74.028,
      "lane": 1,
      "type": "tap"
    },
    {
      "t": 74.234,
      "lane": 1,
      "type": "tap"
    },
    {
      "t": 74.441,
      "lane": 1,
      "type": "tap"
    },
    {
      "t": 74.855,
      "lane": 1,
      "type": "tap"
    },
    {
      "t": 75.062,
      "lane": 1,
      "type": "tap"
    },
    {
      "t": 75.476,
      "lane": 1,
      "type": "tap"
    },
    {
      "t": 75.89,
      "lane": 1,
      "type": "tap"
    },
    {
      "t": 76.303,
      "lane": 1,
      "type": "tap"
    },
    {
      "t": 76.51,
      "lane": 1,
      "type": "tap"
    },
    {
      "t": 77.131,
      "lane": 1,
      "type": "tap"
    },
    {
      "t": 77.338,
      "lane": 1,
      "type": "tap"
    },
    {
      "t": 77.752,
      "lane": 1,
      "type": "tap"
    },
    {
      "t": 77.959,
      "lane": 1,
      "type": "tap"
    },
    {
      "t": 78.166,
      "lane": 1,
      "type": "tap"
    },
    {
      "t": 78.372,
      "lane": 1,
      "type": "tap"
    },
    {
      "t": 78.579,
      "lane": 1,
      "type": "tap"
    },
    {
      "t": 78.786,
      "lane": 1,
      "type": "tap"
    },
    {
      "t": 78.993,
      "lane": 1,
      "type": "tap"
    },
    {
      "t": 79.2,
      "lane": 1,
      "type": "tap"
    },
    {
      "t": 79.407,
      "lane": 1,
      "type": "tap"
    },
    {
      "t": 80.234,
      "lane": 1,
      "type": "tap"
    },
    {
      "t": 80.441,
      "lane": 1,
      "type": "tap"
    },
    {
      "t": 80.648,
      "lane": 1,
      "type": "tap"
    },
    {
      "t": 80.855,
      "lane": 1,
      "type": "tap"
    },
    {
      "t": 81.062,
      "lane": 1,
      "type": "tap"
    }
  ]
}
